fastapi_pagination/__init__.py
fastapi_pagination/api.py
fastapi_pagination/async_paginator.py
fastapi_pagination/bases.py
fastapi_pagination/config.py
fastapi_pagination/cursor.py
fastapi_pagination/customization.py
fastapi_pagination/default.py
fastapi_pagination/errors.py
fastapi_pagination/flow.py
fastapi_pagination/flows.py
fastapi_pagination/iterables.py
fastapi_pagination/limit_offset.py
fastapi_pagination/optional.py
fastapi_pagination/paginator.py
fastapi_pagination/py.typed
fastapi_pagination/types.py
fastapi_pagination/typing_utils.py
fastapi_pagination/utils.py
fastapi_pagination/ext/__init__.py
fastapi_pagination/ext/asyncpg.py
fastapi_pagination/ext/beanie.py
fastapi_pagination/ext/bunnet.py
fastapi_pagination/ext/cassandra.py
fastapi_pagination/ext/databases.py
fastapi_pagination/ext/django.py
fastapi_pagination/ext/elasticsearch.py
fastapi_pagination/ext/firestore.py
fastapi_pagination/ext/gino.py
fastapi_pagination/ext/mongoengine.py
fastapi_pagination/ext/motor.py
fastapi_pagination/ext/odmantic.py
fastapi_pagination/ext/orm.py
fastapi_pagination/ext/ormar.py
fastapi_pagination/ext/piccolo.py
fastapi_pagination/ext/pony.py
fastapi_pagination/ext/py.typed
fastapi_pagination/ext/pymongo.py
fastapi_pagination/ext/sqlalchemy.py
fastapi_pagination/ext/sqlmodel.py
fastapi_pagination/ext/tortoise.py
fastapi_pagination/ext/utils.py
fastapi_pagination/links/__init__.py
fastapi_pagination/links/bases.py
fastapi_pagination/links/default.py
fastapi_pagination/links/limit_offset.py
fastapi_pagination/pydantic/__init__.py
fastapi_pagination/pydantic/common.py
fastapi_pagination/pydantic/consts.py
fastapi_pagination/pydantic/types.py
fastapi_pagination/pydantic/v1.py
fastapi_pagination/pydantic/v2.py
fastapi_pagination-0.15.4.dist-info/METADATA
fastapi_pagination-0.15.4.dist-info/WHEEL
fastapi_pagination-0.15.4.dist-info/licenses/LICENSE
fastapi_pagination-0.15.4.dist-info/RECORD
