Metadata-Version: 2.4
Name: fastapi-pagination
Version: 0.15.4
Summary: FastAPI pagination
Project-URL: Repository, https://github.com/uriyyo/fastapi-pagination
Author-email: Yurii Karabas <1998uriyyo@gmail.com>
License-Expression: MIT
License-File: LICENSE
Classifier: Operating System :: OS Independent
Classifier: Programming Language :: Python
Classifier: Programming Language :: Python :: 3
Classifier: Programming Language :: Python :: 3 :: Only
Classifier: Programming Language :: Python :: 3.10
Classifier: Programming Language :: Python :: 3.11
Classifier: Programming Language :: Python :: 3.12
Classifier: Programming Language :: Python :: 3.13
Classifier: Programming Language :: Python :: 3.14
Requires-Python: >=3.10
Requires-Dist: fastapi>=0.93.0
Requires-Dist: pydantic>=1.9.1
Requires-Dist: typing-extensions>=4.8.0
Provides-Extra: aiosqlite
Requires-Dist: aiosqlite!=0.22.0,>=0.19.0; extra == 'aiosqlite'
Provides-Extra: asyncpg
Requires-Dist: asyncpg>=0.24.0; extra == 'asyncpg'
Requires-Dist: sqlalchemy>=1.3.20; extra == 'asyncpg'
Provides-Extra: beanie
Requires-Dist: beanie>=2.0.0; extra == 'beanie'
Provides-Extra: bunnet
Requires-Dist: bunnet>=1.1.0; extra == 'bunnet'
Provides-Extra: databases
Requires-Dist: databases>=0.6.0; extra == 'databases'
Provides-Extra: django
Requires-Dist: databases>=0.6.0; extra == 'django'
Requires-Dist: django<6.0.0; extra == 'django'
Provides-Extra: elasticsearch
Requires-Dist: elasticsearch-dsl>=8.13.0; extra == 'elasticsearch'
Provides-Extra: firestore
Requires-Dist: google-cloud-firestore>=2.19.0; extra == 'firestore'
Provides-Extra: mongoengine
Requires-Dist: mongoengine>=0.23.1; extra == 'mongoengine'
Provides-Extra: motor
Requires-Dist: motor>=3.6.0; extra == 'motor'
Provides-Extra: odmantic
Requires-Dist: odmantic>=1.0.2; extra == 'odmantic'
Provides-Extra: orm
Requires-Dist: databases>=0.6.0; extra == 'orm'
Requires-Dist: orm>=0.3.1; extra == 'orm'
Provides-Extra: ormar
Provides-Extra: piccolo
Requires-Dist: piccolo>=0.89; extra == 'piccolo'
Provides-Extra: scylla-driver
Requires-Dist: scylla-driver>=3.25.6; extra == 'scylla-driver'
Provides-Extra: sqlalchemy
Requires-Dist: sqlakeyset>=2.0.1680321678; extra == 'sqlalchemy'
Requires-Dist: sqlalchemy>=1.3.20; extra == 'sqlalchemy'
Provides-Extra: sqlmodel
Requires-Dist: sqlakeyset>=2.0.1680321678; extra == 'sqlmodel'
Requires-Dist: sqlmodel>=0.0.22; extra == 'sqlmodel'
Provides-Extra: tortoise
Requires-Dist: tortoise-orm>=0.22.0; extra == 'tortoise'
